LICENSE
MANIFEST.in
README.rst
config.yml.dist
pingdom-run-export
requirements-test.txt
requirements.txt
setup.cfg
setup.py
pingdomexport/__init__.py
pingdomexport/checks.py
pingdomexport/configuration.py
pingdomexport/export.py
pingdomexport/pingdom.py
pingdomexport/utils.py
pingdomexport.egg-info/PKG-INFO
pingdomexport.egg-info/SOURCES.txt
pingdomexport.egg-info/dependency_links.txt
pingdomexport.egg-info/requires.txt
pingdomexport.egg-info/top_level.txt
pingdomexport/load/__init__.py
pingdomexport/load/check_results_mysql.py
pingdomexport/load/check_results_output.py
pingdomexport/load/check_results_postgres.py
pingdomexport/load/checks_load.py
pingdomexport/load/checks_mysql.py
pingdomexport/load/checks_output.py
pingdomexport/load/checks_postgres.py
pingdomexport/load/checks_results_load.py
pingdomexport/tests/__init__.py
pingdomexport/tests/test_checks.py
pingdomexport/tests/test_configuration.py
pingdomexport/tests/test_export.py
pingdomexport/tests/test_pingdom.py
pingdomexport/tests/test_utils.py
pingdomexport/tests/load/__init__.py
pingdomexport/tests/load/test_check_results_mysql.py
pingdomexport/tests/load/test_check_results_output.py
pingdomexport/tests/load/test_check_results_postgres.py
pingdomexport/tests/load/test_checks_load.py
pingdomexport/tests/load/test_checks_mysql.py
pingdomexport/tests/load/test_checks_output.py
pingdomexport/tests/load/test_checks_postgres.py
pingdomexport/tests/load/test_checks_results_load.py