Metadata-Version: 1.1
Name: pingdomexport
Version: 0.1.2
Summary: Export your pingom data to CSV or database
Home-page: https://github.com/entering/pingdomexport
Author: Eduardo Oliveira
Author-email: me@eduardooliveira.net
License: MIT
Keywords: pingdom export mysql postgres
Platform: UNKNOWN
Classifier: Development Status :: 3 - Alpha
Classifier: Environment :: Console
Classifier: Intended Audience :: Developers
Classifier: Intended Audience :: System Administrators
Classifier: License :: OSI Approved :: MIT License
Classifier: Topic :: Utilities
Classifier: Operating System :: OS Independent
Classifier: Programming Language :: Python
Classifier: Programming Language :: Python :: 3.3
Classifier: Programming Language :: Python :: 3.4
Classifier: Programming Language :: Python :: 3.5
